pyflow_acdc/ACDC_OPF.py
pyflow_acdc/ACDC_OPF_model.py
pyflow_acdc/ACDC_PF.py
pyflow_acdc/ACDC_TEP.py
pyflow_acdc/Class_editor.py
pyflow_acdc/Classes.py
pyflow_acdc/Export_files.py
pyflow_acdc/Graph_Dash.py
pyflow_acdc/Graph_and_plot.py
pyflow_acdc/Grid_creator.py
pyflow_acdc/Mapping.py
pyflow_acdc/Market_Coeff.py
pyflow_acdc/Results_class.py
pyflow_acdc/Time_series.py
pyflow_acdc/Time_series_clustering.py
pyflow_acdc/__init__.py
pyflow_acdc/Cable_database/ABB_Al_XLPE_1000mm2_110kV.yaml
pyflow_acdc/Cable_database/ABB_Al_XLPE_1000mm2_132kV.yaml
pyflow_acdc/Cable_database/ABB_Al_XLPE_1000mm2_150kV.yaml
pyflow_acdc/Cable_database/ABB_Al_XLPE_1000mm2_220kV.yaml
pyflow_acdc/Cable_database/ABB_Al_XLPE_1000mm2_275kV.yaml
pyflow_acdc/Cable_database/ABB_Al_XLPE_1000mm2_45kV.yaml
pyflow_acdc/Cable_database/ABB_Al_XLPE_1000mm2_66kV.yaml
pyflow_acdc/Cable_database/ABB_Al_XLPE_120mm2_30kV.yaml
pyflow_acdc/Cable_database/ABB_Al_XLPE_120mm2_45kV.yaml
pyflow_acdc/Cable_database/ABB_Al_XLPE_120mm2_66kV.yaml
pyflow_acdc/Cable_database/ABB_Al_XLPE_150mm2_30kV.yaml
pyflow_acdc/Cable_database/ABB_Al_XLPE_150mm2_45kV.yaml
pyflow_acdc/Cable_database/ABB_Al_XLPE_150mm2_66kV.yaml
pyflow_acdc/Cable_database/ABB_Al_XLPE_185mm2_110kV.yaml
pyflow_acdc/Cable_database/ABB_Al_XLPE_185mm2_132kV.yaml
pyflow_acdc/Cable_database/ABB_Al_XLPE_185mm2_30kV.yaml
pyflow_acdc/Cable_database/ABB_Al_XLPE_185mm2_45kV.yaml
pyflow_acdc/Cable_database/ABB_Al_XLPE_185mm2_66kV.yaml
pyflow_acdc/Cable_database/ABB_Al_XLPE_240mm2_110kV.yaml
pyflow_acdc/Cable_database/ABB_Al_XLPE_240mm2_132kV.yaml
pyflow_acdc/Cable_database/ABB_Al_XLPE_240mm2_150kV.yaml
pyflow_acdc/Cable_database/ABB_Al_XLPE_240mm2_30kV.yaml
pyflow_acdc/Cable_database/ABB_Al_XLPE_240mm2_45kV.yaml
pyflow_acdc/Cable_database/ABB_Al_XLPE_240mm2_66kV.yaml
pyflow_acdc/Cable_database/ABB_Al_XLPE_300mm2_110kV.yaml
pyflow_acdc/Cable_database/ABB_Al_XLPE_300mm2_132kV.yaml
pyflow_acdc/Cable_database/ABB_Al_XLPE_300mm2_150kV.yaml
pyflow_acdc-0.4.0.dist-info/licenses/LICENSE
pyflow_acdc-0.4.0.dist-info/METADATA
pyflow_acdc-0.4.0.dist-info/WHEEL
pyflow_acdc-0.4.0.dist-info/entry_points.txt
pyflow_acdc-0.4.0.dist-info/top_level.txt
pyflow_acdc-0.4.0.dist-info/RECORD
