Metadata-Version: 2.4
Name: pyflow_acdc
Version: 0.4.0
Summary: A python-based tool for the design and analysis of hybrid AC/DC grids
Author-email: Bernardo Castro Valerio <bernardo.castro@upc.edu>
Maintainer-email: Bernardo Castro Valerio <bernardo.castro@upc.edu>
Project-URL: Repository, https://github.com/BernardoCV/pyflow_acdc
Project-URL: Documentation, https://pyflow-acdc.readthedocs.io/en/latest/
Classifier: Development Status :: 3 - Alpha
Classifier: Intended Audience :: Science/Research
Classifier: License :: OSI Approved :: BSD License
Classifier: Programming Language :: C
Classifier: Programming Language :: Python
Classifier: Programming Language :: Python :: 3
Classifier: Programming Language :: Python :: 3.9
Classifier: Programming Language :: Python :: 3.10
Classifier: Programming Language :: Python :: 3.11
Classifier: Programming Language :: Python :: 3.12
Classifier: Programming Language :: Python :: Implementation :: CPython
Classifier: Topic :: Scientific/Engineering
Requires-Python: >=3.9
License-File: LICENSE
Requires-Dist: numpy
Requires-Dist: pandas
Requires-Dist: networkx
Requires-Dist: matplotlib
Requires-Dist: scipy
Requires-Dist: prettytable
Requires-Dist: plotly
Requires-Dist: geopandas
Requires-Dist: pyyaml
Requires-Dist: shapely
Requires-Dist: svgwrite
Requires-Dist: scikit-learn
Requires-Dist: kmedoids
Provides-Extra: mapping
Requires-Dist: folium; extra == "mapping"
Provides-Extra: opf
Requires-Dist: pyomo; extra == "opf"
Provides-Extra: dash
Requires-Dist: dash; extra == "dash"
Dynamic: license-file
